pcs_log/GenVersion.py
pcs_log/LogP.py
pcs_log/__init__.py
pcs_log-1.6.139.240629104654.dist-info/METADATA
pcs_log-1.6.139.240629104654.dist-info/WHEEL
pcs_log-1.6.139.240629104654.dist-info/top_level.txt
pcs_log-1.6.139.240629104654.dist-info/RECORD
