Metadata-Version: 2.1
Name: pcs-log
Version: 1.6.139.240629104654
Summary: Generic logger
Home-page: https://pcs-log.readthedocs.io/en/latest/
Author: Rainer Pietsch
Author-email: r.pietsch@pcs-at.com
License: UNKNOWN
Download-URL: https://github.com/rpietsch1953/Log
Platform: UNKNOWN
Classifier: Programming Language :: Python :: 3
Classifier: License :: OSI Approved :: GNU General Public License v2 (GPLv2)
Classifier: Operating System :: OS Independent
Requires-Python: >=3.6
Requires-Dist: netifaces
Requires-Dist: setproctitle
